slyvek_setup/__init__.py
slyvek_setup/main.py
slyvek_setup/scripts/__init__.py
slyvek_setup/scripts/backup.sh
slyvek_setup/scripts/slyvek.sh
slyvek_setup/templates/__init__.py
slyvek_setup/templates/nginx-backup.conf
slyvek_setup-0.2.3.dist-info/METADATA
slyvek_setup-0.2.3.dist-info/WHEEL
slyvek_setup-0.2.3.dist-info/entry_points.txt
slyvek_setup-0.2.3.dist-info/top_level.txt
slyvek_setup-0.2.3.dist-info/RECORD
